datasetscraper/Scraper.py
datasetscraper/__init__.py
datasetscraper/downloader.py
datasetscraper/pageagent.py
datasetscraper-0.0.4.dist-info/LICENSE
datasetscraper-0.0.4.dist-info/METADATA
datasetscraper-0.0.4.dist-info/WHEEL
datasetscraper-0.0.4.dist-info/top_level.txt
datasetscraper-0.0.4.dist-info/RECORD
