Metadata-Version: 2.1
Name: datasetscraper
Version: 0.0.4
Summary: Tool to create image datasets for machine learning problemsby scraping search engines like Google, Bing and Baidu. 
Home-page: https://github.com/TimeTraveller-San/datasetscraper
Author: Time Traveller
Author-email: time.traveller.san@gmail.com
License: GPLv2
Keywords: dataset_scraper,machine learning,dataset,images,scrape,yandex,google,bing,baidu
Platform: UNKNOWN
Classifier: Programming Language :: Python :: 3
Classifier: Operating System :: POSIX :: Linux
Requires-Python: >=3
Requires-Dist: pyppeteer (>=0.0.25)
Requires-Dist: fastprogress (>=0.1.21)
Requires-Dist: requests (>=2.19.1)
